elasticmagic/__init__.py
elasticmagic/actions.py
elasticmagic/agg.py
elasticmagic/attribute.py
elasticmagic/cluster.py
elasticmagic/compiler.py
elasticmagic/datastructures.py
elasticmagic/document.py
elasticmagic/expression.py
elasticmagic/function.py
elasticmagic/index.py
elasticmagic/result.py
elasticmagic/search.py
elasticmagic/types.py
elasticmagic/util.py
elasticmagic/version.py
elasticmagic/ext/__init__.py
elasticmagic/ext/asyncio/__init__.py
elasticmagic/ext/asyncio/cluster.py
elasticmagic/ext/asyncio/index.py
elasticmagic/ext/asyncio/search.py
elasticmagic/ext/asyncio/pagination/__init__.py
elasticmagic/ext/asyncio/pagination/flask.py
elasticmagic/ext/pagination/__init__.py
elasticmagic/ext/pagination/flask.py
elasticmagic/ext/queryfilter/__init__.py
elasticmagic/ext/queryfilter/codec.py
elasticmagic/ext/queryfilter/queryfilter.py
elasticmagic-0.3.0.dist-info/METADATA
elasticmagic-0.3.0.dist-info/WHEEL
elasticmagic-0.3.0.dist-info/licenses/LICENSE
elasticmagic-0.3.0.dist-info/RECORD
