Metadata-Version: 2.4
Name: elasticmagic
Version: 0.3.0
Summary: Add your description here
Author-email: Alexander Koval <kovalidis@gmail.com>
License-File: LICENSE
Requires-Python: >=3.8
Requires-Dist: elasticsearch<7.14
Requires-Dist: python-dateutil>=2.8.2
Provides-Extra: async
Requires-Dist: elasticsearch[async]<7.14; extra == 'async'
